ifelse/mux2to1.v
/*
 * Mux2to1 using if else
 *
*/

module mux2to1 (w0, w1, s, f);
input w0, w1, s;
output reg f;

always @(w0, w1, s)
begin
	if (s == 0)
		f = w0;
	else
		f = w1;
end

endmodule

ifelse/mux2to1_tb.v

module mux2to1_tb();

//lines to drive declared as variables
reg w0, w1, s;

//outputs signals declared as wires
wire f;

initial begin
	$dumpfile("mux2to1.vcd");
    $dumpvars(0,my_mux2to1);
 
	s = 0; w1 = 0;	w0 = 0;	//Time 0
	
	#1  s = 0; w1 = 0;	w0 = 1;	//#1 introduces a delay =  1 simulation time
	#1  s = 0; w1 = 1;	w0 = 0;	
	#1  s = 0; w1 = 1;	w0 = 1;
	#1  s = 1; w1 = 0;	w0 = 0;		
	#1  s = 1; w1 = 0;	w0 = 1;		
	#1  s = 1; w1 = 1;	w0 = 0;		
	#1  s = 1; w1 = 1;	w0 = 0;		
	#1  s = 1; w1 = 1;	w0 = 1;		
	#1  s = 0; w1 = 0;	w0 = 0;		
	#10 $finish;

end

mux2to1 my_mux2to1(w0,w1,s,f);
endmodule

ifelse/mux2to1.vcd
$date
	Sun Oct  9 15:10:00 2016
$end
$version
	Icarus Verilog
$end
$timescale
	1s
$end
$scope module mux2to1_tb $end
$scope module my_mux2to1 $end
$var wire 1 ! s $end
$var wire 1 " w0 $end
$var wire 1 # w1 $end
$var reg 1 $ f $end
$upscope $end
$upscope $end
$enddefinitions $end
#0
$dumpvars
0$
0#
0"
0!
$end
#1
1$
1"
#2
0$
0"
1#
#3
1$
1"
#4
0$
0"
0#
1!
#5
1"
#6
1$
0"
1#
#8
1"
#9
0$
0"
0#
0!
