fulladd/fulladd.v
/*
 * full-adder implemented using case statement
 *
*/


// Full adder
module fulladd (Cin, x, y, s, Cout);
input Cin, x, y;
output reg s, Cout;

always @(Cin, x, y)
begin
	case ( {Cin, x, y} )
		3'b000: {Cout, s} = 'b00;
		3'b001: {Cout, s} = 'b01;
		3'b010: {Cout, s} = 'b01;
		3'b011: {Cout, s} = 'b10;
		3'b100: {Cout, s} = 'b01;
		3'b101: {Cout, s} = 'b10;
		3'b110: {Cout, s} = 'b10;
		3'b111: {Cout, s} = 'b11;
		//it is good practice to use a default assignment, 
		//otherwise a latch may be inferred for non used
		//combinations
	endcase
end
endmodule

fulladd/fulladd_tb.v

module mux2to1_tb();

//lines to drive declared as variables
reg  Cin, x, y;

//outputs signals declared as wires
wire s, Cout;

initial begin
	$dumpfile("fulladd.vcd");
    $dumpvars(0,my_fulladd);
 
	Cin = 0; x = 0;	y = 0;	//Time 0
	
	#2  Cin = 0; x =0;	y = 1;	//#2 introduces a delay = 2 simulation time
	#2  Cin = 0; x =1;	y = 0;	
	#2  Cin = 0; x =1;	y = 1;
	#2  Cin = 1; x =0;	y = 0;		
	#2  Cin = 1; x =0;	y = 1;		
	#2  Cin = 1; x =1;	y = 0;		
	#2  Cin = 1; x =1;	y = 0;		
	#2  Cin = 1; x =1;	y = 1;		
	#2  Cin = 0; x =0;	y = 0;		
	#10 $finish;

end

fulladd my_fulladd(Cin,x,y,s,Cout);

endmodule

fulladd/fulladd.vcd
$date
	Sun Oct  9 15:58:30 2016
$end
$version
	Icarus Verilog
$end
$timescale
	1s
$end
$scope module mux2to1_tb $end
$scope module my_fulladd $end
$var wire 1 ! Cin $end
$var wire 1 " x $end
$var wire 1 # y $end
$var reg 1 $ Cout $end
$var reg 1 % s $end
$upscope $end
$upscope $end
$enddefinitions $end
#0
$dumpvars
0%
0$
0#
0"
0!
$end
#2
1%
1#
#4
0#
1"
#6
1$
0%
1#
#8
0$
1%
0#
0"
1!
#10
1$
0%
1#
#12
0#
1"
#16
1%
1#
#18
0$
0%
0#
0"
0!
